Metadata-Version: 2.4
Name: slash-command-manager
Version: 0.6.0a7
Summary: A CLI tool for generating and managing slash commands with MCP server support for prompt management
Author-email: Liatrio <labs@liatrio.com>
License: Apache License
License-File: LICENSE
Keywords: ai-assistant,automation,cli,generator,mcp,prompt-management,slash-commands,workflow
Classifier: Development Status :: 4 - Beta
Classifier: Intended Audience :: Developers
Classifier: Operating System :: OS Independent
Classifier: Programming Language :: Python :: 3
Classifier: Programming Language :: Python :: 3.12
Classifier: Topic :: Software Development :: Build Tools
Classifier: Topic :: Software Development :: Libraries :: Python Modules
Classifier: Topic :: Utilities
Requires-Python: >=3.12
Requires-Dist: fastmcp
Requires-Dist: pyyaml>=6.0
Requires-Dist: questionary>=1.10.0
Requires-Dist: requests>=2.31.0
Requires-Dist: rich>=13.0.0
Requires-Dist: tomli-w>=1.0.0
Requires-Dist: typer>=0.9.0
Provides-Extra: dev
Requires-Dist: pexpect>=4.9.0; extra == 'dev'
Requires-Dist: pre-commit>=3.0.0; extra == 'dev'
Requires-Dist: pytest-cov>=4.0.0; extra == 'dev'
Requires-Dist: pytest-httpx>=0.35.0; extra == 'dev'
Requires-Dist: pytest>=7.0.0; extra == 'dev'
Requires-Dist: ruff>=0.1.0; extra == 'dev'
